nocfo_file_downloader/__init__.py
nocfo_file_downloader/__main__.py
nocfo_file_downloader/cli.py
nocfo_file_downloader-0.1.0.dist-info/METADATA
nocfo_file_downloader-0.1.0.dist-info/WHEEL
nocfo_file_downloader-0.1.0.dist-info/entry_points.txt
nocfo_file_downloader-0.1.0.dist-info/licenses/LICENSE
nocfo_file_downloader-0.1.0.dist-info/RECORD
