Metadata-Version: 2.4
Name: nocfo-file-downloader
Version: 0.1.0
Summary: CLI tool to download NoCFO attachments and organize them by document number.
Author: NoCFO
License: MIT License
License-File: LICENSE
Keywords: attachments,cli,download,nocfo
Classifier: Development Status :: 3 - Alpha
Classifier: Intended Audience :: Financial and Insurance Industry
Classifier: License :: OSI Approved :: MIT License
Classifier: Programming Language :: Python :: 3
Classifier: Programming Language :: Python :: 3 :: Only
Classifier: Programming Language :: Python :: 3.9
Classifier: Programming Language :: Python :: 3.10
Classifier: Programming Language :: Python :: 3.11
Classifier: Programming Language :: Python :: 3.12
Classifier: Programming Language :: Python :: 3.13
Requires-Python: >=3.9
Requires-Dist: requests>=2.31.0
Requires-Dist: rich>=13.7.0
Requires-Dist: typer>=0.12.3
